simcat/__init__.py
simcat/agents.py
simcat/interaction.py
simcat/matrix.py
simcat/utils.py
simcat-0.3.2.dist-info/LICENSE.txt
simcat-0.3.2.dist-info/METADATA
simcat-0.3.2.dist-info/WHEEL
simcat-0.3.2.dist-info/top_level.txt
simcat-0.3.2.dist-info/RECORD
