Metadata-Version: 2.1
Name: simcat
Version: 0.3.2
Summary: A Python package to simulate multi-agent cognitive association tasks using embedding spaces
Author-email: Roberta Rocca <rbrrcc@gmail.com>
Project-URL: Homepage, https://github.com/rbroc/simcat
Project-URL: Issues, https://github.com/rbroc/simcat/issues
Keywords: cognition,social interaction,agent-based simulations,foraging,embedding models
Classifier: Programming Language :: Python :: 3
Classifier: Programming Language :: Python :: 3.8
Classifier: Programming Language :: Python :: 3.9
Classifier: Programming Language :: Python :: 3.10
Classifier: License :: OSI Approved :: MIT License
Classifier: Operating System :: OS Independent
Requires-Python: >=3.8
License-File: LICENSE.txt
Requires-Dist: numpy ==1.23.0
Requires-Dist: pandas ==1.4.3
Requires-Dist: scikit-learn ==1.2.1
Requires-Dist: scipy ==1.8.1
Requires-Dist: umap-learn ==0.5.5
Requires-Dist: seaborn ==0.11.2
Requires-Dist: matplotlib ==3.5.2
Provides-Extra: dev
Requires-Dist: black ; extra == 'dev'
Requires-Dist: pytest ; extra == 'dev'
